dapiwrapper/__init__.py
dapiwrapper/functions.py
dapiwrapper-0.0.20.dist-info/METADATA
dapiwrapper-0.0.20.dist-info/WHEEL
dapiwrapper-0.0.20.dist-info/top_level.txt
dapiwrapper-0.0.20.dist-info/RECORD
