Metadata-Version: 2.1
Name: dapiwrapper
Version: 0.0.20
Summary: rpc aggregation
Home-page: UNKNOWN
Author: Dcentralab (Niv Shitrit)
Author-email: <niv@dcentralab.com>
License: UNKNOWN
Keywords: python
Platform: UNKNOWN
Classifier: Development Status :: 1 - Planning
Classifier: Intended Audience :: Developers
Classifier: Programming Language :: Python :: 3
Classifier: Operating System :: Unix
Classifier: Operating System :: MacOS :: MacOS X
Classifier: Operating System :: Microsoft :: Windows
Requires-Dist: requests
